openbook_textbook_engine/.DS_Store
openbook_textbook_engine/__init__.py
openbook_textbook_engine/export_templates/css/standard.css
openbook_textbook_engine/export_templates/html/index.html
openbook_textbook_engine/export_templates/html/pdftemplate.html
openbook_textbook_engine/exports.py
openbook_textbook_engine/main.py
openbook_textbook_engine/sample_textbook/.DS_Store
openbook_textbook_engine/sample_textbook/LICENSE.txt
openbook_textbook_engine/sample_textbook/book/chapters/1.md
openbook_textbook_engine/sample_textbook/book/chapters/2.md
openbook_textbook_engine/sample_textbook/book/chapters/3.md
openbook_textbook_engine/sample_textbook/book/pre-content.md
openbook_textbook_engine/sample_textbook/options.json
openbook_textbook_engine/sample_textbook/out/__tempfile__
openbook_textbook_engine/sample_textbook/out/html/__tempfile__
openbook_textbook_engine-0.1.5.dist-info/METADATA
openbook_textbook_engine-0.1.5.dist-info/WHEEL
openbook_textbook_engine-0.1.5.dist-info/entry_points.txt
openbook_textbook_engine-0.1.5.dist-info/RECORD
