Metadata-Version: 2.1
Name: openbook-textbook-engine
Version: 0.1.5
Summary: A CLI toolkit for authoring Openbook textbooks
Author: William Herring
Author-email: william.herring.au@gmail.com
Requires-Python: >=3.9,<4.0
Classifier: Programming Language :: Python :: 3
Classifier: Programming Language :: Python :: 3.9
Classifier: Programming Language :: Python :: 3.10
Classifier: Programming Language :: Python :: 3.11
Classifier: Programming Language :: Python :: 3.12
Requires-Dist: typer[all] (>=0.12.4,<0.13.0)
Requires-Dist: xmltodict (>=0.13.0,<0.14.0)
